[{"height": 540, "width": 960, "image_id": 0, "dataset": "visdrone", "annotations": [{"category_id": 4, "category_name": "car", "category_name_cn": "汽车", "bbox": [187, 369, 43, 27]}, {"category_id": 4, "category_name": "car", "category_name_cn": "汽车", "bbox": [231, 418, 68, 28]}, {"category_id": 6, "category_name": "truck", "category_name_cn": "卡车", "bbox": [189, 434, 68, 45]}, {"category_id": 4, "category_name": "car", "category_name_cn": "汽车", "bbox": [43, 416, 78, 36]}, {"category_id": 10, "category_name": "motor", "category_name_cn": "摩托车", "bbox": [98, 439, 36, 24]}, {"category_id": 2, "category_name": "people", "category_name_cn": "人", "bbox": [109, 435, 13, 23]}, {"category_id": 5, "category_name": "van", "category_name_cn": "面包车", "bbox": [30, 512, 60, 28]}, {"category_id": 5, "category_name": "van", "category_name_cn": "面包车", "bbox": [325, 368, 43, 32]}, {"category_id": 4, "category_name": "car", "category_name_cn": "汽车", "bbox": [326, 344, 43, 26]}, {"category_id": 4, "category_name": "car", "category_name_cn": "汽车", "bbox": [379, 330, 48, 20]}, {"category_id": 10, "category_name": "motor", "category_name_cn": "摩托车", "bbox": [400, 301, 5, 13]}, {"category_id": 7, "category_name": "tricycle", "category_name_cn": "三轮车", "bbox": [445, 278, 20, 18]}, {"category_id": 4, "category_name": "car", "category_name_cn": "汽车", "bbox": [412, 313, 45, 21]}, {"category_id": 3, "category_name": "bicycle", "category_name_cn": "自行车", "bbox": [432, 332, 15, 11]}, {"category_id": 3, "category_name": "bicycle", "category_name_cn": "自行车", "bbox": [442, 330, 14, 10]}, {"category_id": 3, "category_name": "bicycle", "category_name_cn": "自行车", "bbox": [455, 334, 16, 16]}, {"category_id": 1, "category_name": "pedestrian", "category_name_cn": "行人", "bbox": [479, 318, 6, 14]}, {"category_id": 5, "category_name": "van", "category_name_cn": "面包车", "bbox": [468, 304, 39, 24]}, {"category_id": 4, "category_name": "car", "category_name_cn": "汽车", "bbox": [482, 300, 37, 17]}, {"category_id": 4, "category_name": "car", "category_name_cn": "汽车", "bbox": [521, 284, 31, 19]}, {"category_id": 4, "category_name": "car", "category_name_cn": "汽车", "bbox": [525, 275, 33, 17]}, {"category_id": 4, "category_name": "car", "category_name_cn": "汽车", "bbox": [473, 336, 35, 25]}, {"category_id": 5, "category_name": "van", "category_name_cn": "面包车", "bbox": [421, 353, 48, 40]}, {"category_id": 10, "category_name": "motor", "category_name_cn": "摩托车", "bbox": [553, 462, 16, 24]}, {"category_id": 2, "category_name": "people", "category_name_cn": "人", "bbox": [555, 462, 12, 17]}, {"category_id": 4, "category_name": "car", "category_name_cn": "汽车", "bbox": [558, 388, 42, 37]}, {"category_id": 4, "category_name": "car", "category_name_cn": "汽车", "bbox": [547, 273, 31, 16]}, {"category_id": 4, "category_name": "car", "category_name_cn": "汽车", "bbox": [562, 268, 30, 15]}, {"category_id": 4, "category_name": "car", "category_name_cn": "汽车", "bbox": [570, 251, 20, 12]}, {"category_id": 10, "category_name": "motor", "category_name_cn": "摩托车", "bbox": [586, 230, 11, 7]}, {"category_id": 4, "category_name": "car", "category_name_cn": "汽车", "bbox": [569, 283, 23, 16]}, {"category_id": 4, "category_name": "car", "category_name_cn": "汽车", "bbox": [591, 274, 19, 15]}, {"category_id": 5, "category_name": "van", "category_name_cn": "面包车", "bbox": [593, 253, 18, 17]}, {"category_id": 10, "category_name": "motor", "category_name_cn": "摩托车", "bbox": [801, 415, 13, 18]}, {"category_id": 3, "category_name": "bicycle", "category_name_cn": "自行车", "bbox": [812, 417, 10, 17]}, {"category_id": 4, "category_name": "car", "category_name_cn": "汽车", "bbox": [802, 460, 84, 46]}, {"category_id": 5, "category_name": "van", "category_name_cn": "面包车", "bbox": [781, 321, 25, 28]}, {"category_id": 6, "category_name": "truck", "category_name_cn": "卡车", "bbox": [801, 314, 28, 18]}, {"category_id": 4, "category_name": "car", "category_name_cn": "汽车", "bbox": [855, 348, 27, 28]}, {"category_id": 6, "category_name": "truck", "category_name_cn": "卡车", "bbox": [818, 356, 33, 40]}, {"category_id": 4, "category_name": "car", "category_name_cn": "汽车", "bbox": [829, 342, 24, 27]}, {"category_id": 9, "category_name": "bus", "category_name_cn": "公共汽车", "bbox": [788, 290, 46, 27]}, {"category_id": 5, "category_name": "van", "category_name_cn": "面包车", "bbox": [823, 307, 42, 21]}, {"category_id": 6, "category_name": "truck", "category_name_cn": "卡车", "bbox": [869, 271, 12, 15]}, {"category_id": 6, "category_name": "truck", "category_name_cn": "卡车", "bbox": [860, 254, 10, 14]}, {"category_id": 6, "category_name": "truck", "category_name_cn": "卡车", "bbox": [848, 259, 9, 11]}, {"category_id": 4, "category_name": "car", "category_name_cn": "汽车", "bbox": [612, 243, 26, 11]}, {"category_id": 4, "category_name": "car", "category_name_cn": "汽车", "bbox": [680, 252, 16, 13]}, {"category_id": 4, "category_name": "car", "category_name_cn": "汽车", "bbox": [642, 245, 16, 11]}, {"category_id": 5, "category_name": "van", "category_name_cn": "面包车", "bbox": [654, 232, 17, 17]}, {"category_id": 5, "category_name": "van", "category_name_cn": "面包车", "bbox": [668, 228, 11, 12]}, {"category_id": 4, "category_name": "car", "category_name_cn": "汽车", "bbox": [685, 226, 13, 10]}, {"category_id": 1, "category_name": "pedestrian", "category_name_cn": "行人", "bbox": [682, 225, 3, 9]}, {"category_id": 4, "category_name": "car", "category_name_cn": "汽车", "bbox": [619, 235, 25, 14]}, {"category_id": 4, "category_name": "car", "category_name_cn": "汽车", "bbox": [720, 202, 9, 7]}, {"category_id": 4, "category_name": "car", "category_name_cn": "汽车", "bbox": [724, 198, 12, 7]}, {"category_id": 7, "category_name": "tricycle", "category_name_cn": "三轮车", "bbox": [748, 248, 10, 12]}, {"category_id": 2, "category_name": "people", "category_name_cn": "人", "bbox": [752, 249, 5, 7]}, {"category_id": 2, "category_name": "people", "category_name_cn": "人", "bbox": [715, 306, 6, 10]}, {"category_id": 4, "category_name": "car", "category_name_cn": "汽车", "bbox": [757, 200, 8, 7]}, {"category_id": 4, "category_name": "car", "category_name_cn": "汽车", "bbox": [785, 202, 8, 7]}, {"category_id": 4, "category_name": "car", "category_name_cn": "汽车", "bbox": [776, 186, 8, 5]}, {"category_id": 4, "category_name": "car", "category_name_cn": "汽车", "bbox": [799, 182, 8, 7]}, {"category_id": 4, "category_name": "car", "category_name_cn": "汽车", "bbox": [831, 220, 20, 8]}, {"category_id": 4, "category_name": "car", "category_name_cn": "汽车", "bbox": [841, 219, 21, 8]}, {"category_id": 6, "category_name": "truck", "category_name_cn": "卡车", "bbox": [857, 207, 24, 13]}, {"category_id": 4, "category_name": "car", "category_name_cn": "汽车", "bbox": [861, 201, 13, 6]}, {"category_id": 4, "category_name": "car", "category_name_cn": "汽车", "bbox": [866, 197, 15, 6]}, {"category_id": 4, "category_name": "car", "category_name_cn": "汽车", "bbox": [837, 213, 21, 9]}, {"category_id": 4, "category_name": "car", "category_name_cn": "汽车", "bbox": [838, 211, 20, 7]}, {"category_id": 4, "category_name": "car", "category_name_cn": "汽车", "bbox": [808, 186, 7, 6]}, {"category_id": 4, "category_name": "car", "category_name_cn": "汽车", "bbox": [746, 187, 7, 6]}, {"category_id": 4, "category_name": "car", "category_name_cn": "汽车", "bbox": [753, 184, 6, 5]}, {"category_id": 4, "category_name": "car", "category_name_cn": "汽车", "bbox": [759, 181, 6, 4]}, {"category_id": 4, "category_name": "car", "category_name_cn": "汽车", "bbox": [771, 175, 5, 5]}, {"category_id": 4, "category_name": "car", "category_name_cn": "汽车", "bbox": [774, 172, 5, 5]}, {"category_id": 4, "category_name": "car", "category_name_cn": "汽车", "bbox": [777, 171, 4, 4]}, {"category_id": 4, "category_name": "car", "category_name_cn": "汽车", "bbox": [798, 168, 4, 5]}, {"category_id": 9, "category_name": "bus", "category_name_cn": "公共汽车", "bbox": [787, 167, 7, 7]}, {"category_id": 4, "category_name": "car", "category_name_cn": "汽车", "bbox": [803, 168, 7, 4]}, {"category_id": 4, "category_name": "car", "category_name_cn": "汽车", "bbox": [808, 172, 4, 3]}, {"category_id": 4, "category_name": "car", "category_name_cn": "汽车", "bbox": [810, 169, 4, 5]}, {"category_id": 10, "category_name": "motor", "category_name_cn": "摩托车", "bbox": [797, 195, 3, 4]}, {"category_id": 2, "category_name": "people", "category_name_cn": "人", "bbox": [797, 194, 3, 4]}], "file_name": "0000249_03900_d_0000011.jpg"}]